scim2_filter_parser/__init__.py
scim2_filter_parser/ast.py
scim2_filter_parser/attr_paths.py
scim2_filter_parser/lexer.py
scim2_filter_parser/parser.py
scim2_filter_parser/queries/__init__.py
scim2_filter_parser/queries/sql.py
scim2_filter_parser/transpilers/__init__.py
scim2_filter_parser/transpilers/django_q_object.py
scim2_filter_parser/transpilers/sql.py
scim2_filter_parser-0.6.0.dist-info/LICENSE.txt
scim2_filter_parser-0.6.0.dist-info/METADATA
scim2_filter_parser-0.6.0.dist-info/WHEEL
scim2_filter_parser-0.6.0.dist-info/entry_points.txt
scim2_filter_parser-0.6.0.dist-info/RECORD
