Metadata-Version: 2.1
Name: scim2-filter-parser
Version: 0.6.0
Summary: A customizable parser/transpiler for SCIM2.0 filters.
Home-page: https://pypi.org/project/scim2-filter-parser/
License: MIT
Keywords: scim,scim2,2.0,filter
Author: Paul Logston
Author-email: paul@15five.com
Maintainer: Paul Logston
Maintainer-email: paul.logston@gmail.com
Requires-Python: >=3.8
Classifier: Development Status :: 5 - Production/Stable
Classifier: Environment :: Web Environment
Classifier: Intended Audience :: Developers
Classifier: License :: OSI Approved :: MIT License
Classifier: Natural Language :: English
Classifier: Operating System :: OS Independent
Classifier: Programming Language :: Python :: 3
Classifier: Programming Language :: Python :: 3.8
Classifier: Programming Language :: Python :: 3.9
Classifier: Programming Language :: Python :: 3.10
Classifier: Programming Language :: Python :: 3.11
Classifier: Programming Language :: Python :: 3.12
Classifier: Topic :: Internet
Classifier: Topic :: Software Development :: Libraries :: Python Modules
Provides-Extra: django-query
Requires-Dist: django (>=3.2) ; extra == "django-query"
Requires-Dist: sly (==0.5)
Project-URL: Documentation, https://scim2-filter-parser.readthedocs.io/en/stable/
Project-URL: Repository, https://github.com/15five/scim2-filter-parser
